replicpy/__init__.py
replicpy/core/__init__.py
replicpy/core/response.py
replicpy/core/server.py
replicpy/core/setups.py
replicPy-0.1.1.dist-info/LICENCE.txt
replicPy-0.1.1.dist-info/METADATA
replicPy-0.1.1.dist-info/WHEEL
replicPy-0.1.1.dist-info/top_level.txt
replicPy-0.1.1.dist-info/RECORD
