Metadata-Version: 2.1
Name: replicPy
Version: 0.1.1
Summary: A sample Python framework
Home-page: https://github.com/sudheeshsubash/ReplicPy
Author: sudheesh s
Author-email: sudheeshsubhash834@gmail.com
License: MIT
Classifier: Development Status :: 3 - Alpha
Classifier: Intended Audience :: Developers
Classifier: Operating System :: Microsoft :: Windows
Classifier: Topic :: Software Development :: Libraries
Classifier: License :: OSI Approved :: MIT License
Classifier: Programming Language :: Python :: 3
License-File: LICENCE.txt
Requires-Dist: Jinja2 (>=3.1.2)
